colorsys.py
adafruit_circuitpython_colorsys-3.0.3.dist-info/licenses/LICENSE
adafruit_circuitpython_colorsys-3.0.3.dist-info/METADATA
adafruit_circuitpython_colorsys-3.0.3.dist-info/WHEEL
adafruit_circuitpython_colorsys-3.0.3.dist-info/top_level.txt
adafruit_circuitpython_colorsys-3.0.3.dist-info/RECORD
